ehrzero/.DS_Store
ehrzero/__init__.py
ehrzero/dataviz.py
ehrzero/ehrzero.py
ehrzero/etiology.py
ehrzero/feature_engineering.py
ehrzero/preprocessing.py
ehrzero/tools.py
ehrzero/tuning.py
ehrzero/z3.py
ehrzero/MODELS/F/IMPUTER.pickle
ehrzero/MODELS/F/LGBM.pickle
ehrzero/MODELS/F/NB.pickle
ehrzero/MODELS/F/NB_SCALER.pickle
ehrzero/MODELS/F/ROC_F_100.csv
ehrzero/MODELS/F/ROC_F_125.csv
ehrzero/MODELS/F/ROC_F_150.csv
ehrzero/MODELS/F/ROC_F_25.csv
ehrzero/MODELS/F/ROC_F_50.csv
ehrzero/MODELS/F/ROC_F_75.csv
ehrzero/MODELS/M/IMPUTER.pickle
ehrzero/MODELS/M/LGBM.pickle
ehrzero/MODELS/M/NB.pickle
ehrzero/MODELS/M/NB_SCALER.pickle
ehrzero/MODELS/M/ROC_M_100.csv
ehrzero/MODELS/M/ROC_M_125.csv
ehrzero/MODELS/M/ROC_M_150.csv
ehrzero/MODELS/M/ROC_M_25.csv
ehrzero/MODELS/M/ROC_M_50.csv
ehrzero/MODELS/M/ROC_M_75.csv
ehrzero/PFSA/F/Cardiovascular/NEG.pfsa
ehrzero/PFSA/F/Cardiovascular/POS.pfsa
ehrzero/PFSA/F/Development/NEG.pfsa
ehrzero/PFSA/F/Development/POS.pfsa
ehrzero/PFSA/F/Digestive/NEG.pfsa
ehrzero/PFSA/F/Digestive/POS.pfsa
ehrzero/PFSA/F/Endocrine/NEG.pfsa
ehrzero/PFSA/F/Endocrine/POS.pfsa
ehrzero/PFSA/F/Hematologic/NEG.pfsa
ehrzero/PFSA/F/Hematologic/POS.pfsa
ehrzero/PFSA/F/Immune/NEG.pfsa
ehrzero/PFSA/F/Immune/POS.pfsa
ehrzero/PFSA/F/Infectious_Disease/NEG.pfsa
ehrzero/PFSA/F/Infectious_Disease/POS.pfsa
ehrzero/PFSA/F/Integumentary/NEG.pfsa
ehrzero/PFSA/F/Integumentary/POS.pfsa
ehrzero/PFSA/F/Metabolic/NEG.pfsa
ehrzero/PFSA/F/Metabolic/POS.pfsa
ehrzero/PFSA/F/Musculoskeletal/NEG.pfsa
ehrzero/PFSA/F/Musculoskeletal/POS.pfsa
ehrzero/PFSA/F/Ophthalmological/NEG.pfsa
ehrzero/PFSA/F/Ophthalmological/POS.pfsa
ehrzero/PFSA/F/Otic/NEG.pfsa
ehrzero/PFSA/F/Otic/POS.pfsa
ehrzero/PFSA/F/Reproductive/NEG.pfsa
ehrzero/PFSA/F/Reproductive/POS.pfsa
ehrzero/PFSA/F/Respiratory/NEG.pfsa
ehrzero/PFSA/F/Respiratory/POS.pfsa
ehrzero/PFSA/M/Cardiovascular/NEG.pfsa
ehrzero/PFSA/M/Cardiovascular/POS.pfsa
ehrzero/PFSA/M/Development/NEG.pfsa
ehrzero/PFSA/M/Development/POS.pfsa
ehrzero-1.0.20.dist-info/LICENSE
ehrzero-1.0.20.dist-info/METADATA
ehrzero-1.0.20.dist-info/WHEEL
ehrzero-1.0.20.dist-info/top_level.txt
ehrzero-1.0.20.dist-info/RECORD
