Metadata-Version: 2.1
Name: ehrzero
Version: 1.0.20
Summary: Zero-Knowledge Risk Oracle for predictive diagnoses from spare  electronic health records
Home-page: http://zed.uchicago.edu/
Author: Ishanu Chattopadhyay, Dymtro Onishchenko
Author-email: ishanu@uchicago.edu
License: UNKNOWN
Platform: UNKNOWN
Classifier: Programming Language :: Python :: 3
Classifier: License :: OSI Approved :: MIT License
Classifier: Operating System :: OS Independent
Requires-Dist: pandas (>=0.23.4)
Requires-Dist: scikit-learn (>=0.20.3)
Requires-Dist: lightgbm (>=2.2.3)
Requires-Dist: matplotlib (>=3.0.2)
